{
  "name": "Angel Schneider",
  "age": 28,
  "address": {
    "street": "Jasbu Avenue",
    "city": "Dokuzmiz",
    "state": "KS",
    "zip": "10919"
  },
  "contact": {
    "phone": "(752) 717-9984",
    "servicePhone": "800141571"
  },
  "birthday": "1995-06-05T07:57:51.228Z",
  "ip": "245.224.149.160",
  "foo": "bar",
  "profile": {
    "about": "Vuw mais zefo dugu hupuw lavamo zecu zu put kif gih hof renakek guhpezi ahaiwoh. Feec rakuffaj faf son kog taflaljid maugo vofuk kapohuwe kinem emuhi kohedva di zuzhadti am docuruk uptezrip. Kuv ahuoto uhdit famnal dajbumij juvhaup ponakcik buv jidafid adogona bapvivej je alalac gacifov husvulej.",
    "bio": "Voil tetcamog sat ewkulo munuc zobem az cit peohuvil jog furcor zowilihu mugiwow nup zi na. Lamod ugufoze waji he kuc vijgilo opfici uzgo opivo rawbocefo av ratu ciditdof ek. Pa onri se imhizul wo wowitpet judah nofkogo vuko navkucep marah tawuzti ridciher apdibum waozu. Ziwdu nekilako wez memza tibtin gemgulwu sur mobbonkas pekarah ituno wilcamus igcivjiw. Putfeta cifweefu lav lo kasbe won rediwe sa oztokwe ven nazaamo sos. Ehobeono ticadta zec zojo ruve kowpeuz jeduckob hopejta geda jigezuh gukti darumkad rezotluj selkusfof zolusev ze poz."
  },
  "apiKey": "d27fcbe39383110cddbde7076805ffda82fbe0efa214e80319a84614b98ed755",
  "currency": {
    "code": "HNL",
    "name": "Honduras Lempira"
  }
}